AUTHORS.txt
CHANGES.rst
CLASSIFIERS.txt
LICENSE
MANIFEST.in
README.rst
REQUIREMENTS.txt
setup.py
gitwebui/__init__.py
gitwebui/__init__.pyc
gitwebui/blueprint.py
gitwebui/blueprint.pyc
gitwebui/main.py
gitwebui/main.pyc
gitwebui/uwsgi.py
gitwebui.egg-info/PKG-INFO
gitwebui.egg-info/SOURCES.txt
gitwebui.egg-info/dependency_links.txt
gitwebui.egg-info/entry_points.txt
gitwebui.egg-info/requires.txt
gitwebui.egg-info/top_level.txt
gitwebui/static/index.html
gitwebui/static/css/bootstrap.css
gitwebui/static/css/git-webui.css
gitwebui/static/font-awesome/HELP-US-OUT.txt
gitwebui/static/font-awesome/css/font-awesome.css
gitwebui/static/font-awesome/css/font-awesome.min.css
gitwebui/static/font-awesome/fonts/FontAwesome.otf
gitwebui/static/font-awesome/fonts/fontawesome-webfont.eot
gitwebui/static/font-awesome/fonts/fontawesome-webfont.svg
gitwebui/static/font-awesome/fonts/fontawesome-webfont.ttf
gitwebui/static/font-awesome/fonts/fontawesome-webfont.woff
gitwebui/static/font-awesome/fonts/fontawesome-webfont.woff2
gitwebui/static/font-awesome/less/animated.less
gitwebui/static/font-awesome/less/bordered-pulled.less
gitwebui/static/font-awesome/less/core.less
gitwebui/static/font-awesome/less/fixed-width.less
gitwebui/static/font-awesome/less/font-awesome.less
gitwebui/static/font-awesome/less/icons.less
gitwebui/static/font-awesome/less/larger.less
gitwebui/static/font-awesome/less/list.less
gitwebui/static/font-awesome/less/mixins.less
gitwebui/static/font-awesome/less/path.less
gitwebui/static/font-awesome/less/rotated-flipped.less
gitwebui/static/font-awesome/less/screen-reader.less
gitwebui/static/font-awesome/less/stacked.less
gitwebui/static/font-awesome/less/variables.less
gitwebui/static/font-awesome/scss/_animated.scss
gitwebui/static/font-awesome/scss/_bordered-pulled.scss
gitwebui/static/font-awesome/scss/_core.scss
gitwebui/static/font-awesome/scss/_fixed-width.scss
gitwebui/static/font-awesome/scss/_icons.scss
gitwebui/static/font-awesome/scss/_larger.scss
gitwebui/static/font-awesome/scss/_list.scss
gitwebui/static/font-awesome/scss/_mixins.scss
gitwebui/static/font-awesome/scss/_path.scss
gitwebui/static/font-awesome/scss/_rotated-flipped.scss
